.gitignore
.travis.yml
LICENSE
Pipfile
README.md
setup.cfg
setup.py
docs/Makefile
docs/conf.py
docs/index.rst
docs/piripherals.bus.rst
docs/piripherals.button.rst
docs/piripherals.event.rst
docs/piripherals.led.rst
docs/piripherals.mpd.rst
docs/piripherals.mpr121.rst
docs/piripherals.util.rst
docs/_static/custom.css
docs/_static/logo.md
docs/_static/logo.png
docs/_static/logo.svg
piripherals/__init__.py
piripherals/__version__.py
piripherals/bus.py
piripherals/button.py
piripherals/event.py
piripherals/led.py
piripherals/mpd.py
piripherals/mpr121.py
piripherals/util.py
piripherals.egg-info/PKG-INFO
piripherals.egg-info/SOURCES.txt
piripherals.egg-info/dependency_links.txt
piripherals.egg-info/entry_points.txt
piripherals.egg-info/requires.txt
piripherals.egg-info/top_level.txt
tests/__init__.py
tests/test_bus.py
tests/test_button.py
tests/test_event.py
tests/test_led.py
tests/test_mpd.py
tests/test_mpr121.py
tests/test_util.py